easyPWD_Generate/__init__.py
easyPWD_Generate-0.1.dist-info/LICENCE.txt
easyPWD_Generate-0.1.dist-info/METADATA
easyPWD_Generate-0.1.dist-info/WHEEL
easyPWD_Generate-0.1.dist-info/top_level.txt
easyPWD_Generate-0.1.dist-info/RECORD
