Metadata-Version: 2.1
Name: easyPWD-Generate
Version: 0.1
Summary: generate
Author: 17med achour
Author-email: ahmedbenachour2003beta@gmail.com
Classifier: Programming Language :: Python :: 3
Classifier: License :: OSI Approved :: MIT License
Classifier: Operating System :: OS Independent
License-File: LICENCE.txt
